grampyx/__init__.py
grampyx/_base_functions.py
grampyx/error_handling.py
grampyx/grampyx.py
grampyx/mappings.py
grampyx-0.2.2.dist-info/LICENSE
grampyx-0.2.2.dist-info/METADATA
grampyx-0.2.2.dist-info/WHEEL
grampyx-0.2.2.dist-info/top_level.txt
grampyx-0.2.2.dist-info/RECORD
