Metadata-Version: 2.1
Name: grampyx
Version: 0.2.2
Summary: Convert text to image
Home-page: https://github.com/cbattle12/grampyx
Author: Christopher Battle
Author-email: christopher.g.battle@gmail.com
License: MIT
Platform: UNKNOWN
Classifier: License :: OSI Approved :: MIT License
Classifier: Programming Language :: Python :: 3
Requires-Python: >=3.5
Requires-Dist: numpy (>=1.15.0)
